OGRE/__init__.py
OGRE/datasets/DBLP.txt
OGRE/datasets/Flickr.mat
OGRE/datasets/Pubmed.txt
OGRE/embeddings_degrees/DBLP + node2vec + OGRE + 100.npy
OGRE/embeddings_state_of_the_art/Cora + node2vec.npy
OGRE/evaluation_tasks/__init__.py
OGRE/evaluation_tasks/calculate_non_edges.py
OGRE/evaluation_tasks/calculate_static_embeddings.py
OGRE/evaluation_tasks/eval_utils.py
OGRE/evaluation_tasks/link_prediction.py
OGRE/evaluation_tasks/node_classification.py
OGRE/evaluation_tasks/non_edges_Cora.csv
OGRE/evaluation_tasks/plot_results.py
OGRE/evaluation_tasks/plots_utils.py
OGRE/files_degrees/Cora_results_lp.csv
OGRE/labels/dblp_tags.txt
OGRE/labels/pubmed2_tags.txt
OGRE/our_embeddings_methods/D_W_OGRE.py
OGRE/our_embeddings_methods/OGRE.py
OGRE/our_embeddings_methods/__init__.py
OGRE/our_embeddings_methods/static_embeddings.py
OGRE/our_embeddings_methods/utils.py
OGRE/plots/DBLP Link Prediction AUC  initial.png
OGRE/plots/DBLP Link Prediction AUC.png
OGRE/plots/DBLP separated times HOPE.png
OGRE/plots/Pubmed Node Classification  Micro-F1 initial.png
OGRE/plots/Pubmed Node Classification Micro-F1.png
OGRE/state_of_the_art/__init__.py
OGRE/state_of_the_art/state_of_the_art_embedding.py
OGRE/state_of_the_art/gcn/__init__.py
OGRE/state_of_the_art/gcn/layers.py
OGRE/state_of_the_art/gcn/models.py
OGRE/state_of_the_art/gcn/utils.py
OGRE_embed-0.0.3.dist-info/METADATA
OGRE_embed-0.0.3.dist-info/WHEEL
OGRE_embed-0.0.3.dist-info/top_level.txt
OGRE_embed-0.0.3.dist-info/RECORD
