Metadata-Version: 2.1
Name: OGRE-embed
Version: 0.0.3
Summary: Online Two-Stages Embedding Method For Large Graphs
Home-page: https://github.com/AmitKabya/OGRE
Author: Shoval Fridman
Maintainer: Amit Kabya
Maintainer-email: kabya.amit@gmail.com
License: MIT
Keywords: graphs networks graph-embeddings
Requires-Python: >=3.6.8
Requires-Dist: setuptools (>=61.3.1)
